fraggler/__init__.py
fraggler/fraggler.py
fraggler/ladders.py
fraggler-3.0.3.dist-info/LICENSE
fraggler-3.0.3.dist-info/METADATA
fraggler-3.0.3.dist-info/WHEEL
fraggler-3.0.3.dist-info/entry_points.txt
fraggler-3.0.3.dist-info/top_level.txt
fraggler-3.0.3.dist-info/RECORD
