Metadata-Version: 2.1
Name: fraggler
Version: 3.0.3
Summary: Fragment Analysis package in python!
Home-page: https://github.com/willros/fraggler
Author: William Rosenbaum and Pär Larsson
Author-email: william.rosenbaum@umu.se
License: MIT
Requires-Python: >=3.10
License-File: LICENSE
Requires-Dist: pandas==2.2.2
Requires-Dist: numpy==1.26.4
Requires-Dist: scikit-learn==1.5.0
Requires-Dist: matplotlib==3.9.0
Requires-Dist: lmfit==1.3.1
Requires-Dist: scipy==1.13.1
Requires-Dist: biopython==1.83
Requires-Dist: panel==1.4.4
Requires-Dist: altair==5.3.0
Requires-Dist: setuptools
Requires-Dist: pandas-flavor==0.6.0
